{
  "pm2_5_t+3h": {
    "model": "catboost_regressor",
    "cv_score": 0.942249,
    "rmse": 11.50574,
    "mse": 132.382054,
    "r2": 0.942249,
    "mae": 7.979769,
    "trained_at": "2025-08-15T07:28:48.632058Z",
    "model_path": "models\\pm2_5_tplus3h_best.joblib",
    "shap_summary": "models\\shap\\pm2_5_tplus6h_shap.csv"
  },
  "pm2_5_t+6h": {
    "model": "lightgbm_regressor",
    "cv_score": 0.924752,
    "rmse": 12.998783,
    "mse": 168.968363,
    "r2": 0.924752,
    "mae": 9.223719,
    "trained_at": "2025-08-15T07:30:54.175202Z",
    "model_path": "models\\pm2_5_tplus6h_best.joblib",
    "shap_summary": "models\\shap\\pm2_5_tplus6h_shap.csv"
  },
  "pm10_t+3h": {
    "model": "lightgbm_regressor",
    "cv_score": 0.904192,
    "rmse": 23.066411,
    "mse": 532.059305,
    "r2": 0.904192,
    "mae": 14.662915,
    "trained_at": "2025-08-15T07:31:49.458058Z",
    "model_path": "models\\pm10_tplus3h_best.joblib",
    "shap_summary": "models\\shap\\pm10_tplus3h_shap.csv"
  },
  "pm10_t+6h": {
    "model": "xgboost_regressor",
    "cv_score": 0.841179,
    "rmse": 28.894651,
    "mse": 834.900857,
    "r2": 0.841179,
    "mae": 18.573502,
    "trained_at": "2025-08-15T07:32:44.598689Z",
    "model_path": "models\\pm10_tplus6h_best.joblib",
    "shap_summary": "models\\shap\\pm10_tplus6h_shap.csv"
  }
}